{".class": "MypyFile", "_fullname": "app", "is_partial_stub_package": false, "is_stub": false, "names": {".class": "SymbolTable", "Cust_Input": {".class": "SymbolTableNode", "kind": "Gdef", "node": {".class": "TypeInfo", "_promote": null, "abstract_attributes": [], "bases": ["builtins.object"], "declared_metaclass": null, "defn": {".class": "ClassDef", "fullname": "app.Cust_Input", "name": "Cust_Input", "type_vars": []}, "flags": [], "fullname": "app.Cust_Input", "metaclass_type": null, "metadata": {}, "module_name": "app", "mro": ["app.Cust_Input", "builtins.object"], "names": {".class": "SymbolTable", "Dates_list": {".class": "SymbolTableNode", "implicit": true, "kind": "Mdef", "node": {".class": "Var", "flags": [], "fullname": "app.Cust_Input.Dates_list", "name": "Dates_list", "type": {".class": "AnyType", "missing_import_name": null, "source_any": null, "type_of_any": 1}}}, "Locations_list": {".class": "SymbolTableNode", "implicit": true, "kind": "Mdef", "node": {".class": "Var", "flags": [], "fullname": "app.Cust_Input.Locations_list", "name": "Locations_list", "type": {".class": "AnyType", "missing_import_name": null, "source_any": null, "type_of_any": 1}}}, "Locations_type": {".class": "SymbolTableNode", "implicit": true, "kind": "Mdef", "node": {".class": "Var", "flags": [], "fullname": "app.Cust_Input.Locations_type", "name": "Locations_type", "type": {".class": "AnyType", "missing_import_name": null, "source_any": null, "type_of_any": 1}}}, "Money_list": {".class": "SymbolTableNode", "implicit": true, "kind": "Mdef", "node": {".class": "Var", "flags": [], "fullname": "app.Cust_Input.Money_list", "name": "Money_list", "type": {".class": "AnyType", "missing_import_name": null, "source_any": null, "type_of_any": 1}}}, "__init__": {".class": "SymbolTableNode", "kind": "Mdef", "node": {".class": "FuncDef", "arg_kinds": [0, 0, 0, 0, 0, 0, 0, 0, 0, 0, 0, 0], "arg_names": ["self", "cnt", "cnt_return", "cnt_money", "no_bud", "one_way", "text", "Locations_list", "Locations_type", "Dates_list", "Money_list", "response"], "flags": [], "fullname": "app.Cust_Input.__init__", "name": "__init__", "type": null}}, "cnt": {".class": "SymbolTableNode", "implicit": true, "kind": "Mdef", "node": {".class": "Var", "flags": [], "fullname": "app.Cust_Input.cnt", "name": "cnt", "type": {".class": "AnyType", "missing_import_name": null, "source_any": null, "type_of_any": 1}}}, "cnt_money": {".class": "SymbolTableNode", "implicit": true, "kind": "Mdef", "node": {".class": "Var", "flags": [], "fullname": "app.Cust_Input.cnt_money", "name": "cnt_money", "type": {".class": "AnyType", "missing_import_name": null, "source_any": null, "type_of_any": 1}}}, "cnt_return": {".class": "SymbolTableNode", "implicit": true, "kind": "Mdef", "node": {".class": "Var", "flags": [], "fullname": "app.Cust_Input.cnt_return", "name": "cnt_return", "type": {".class": "AnyType", "missing_import_name": null, "source_any": null, "type_of_any": 1}}}, "no_bud": {".class": "SymbolTableNode", "implicit": true, "kind": "Mdef", "node": {".class": "Var", "flags": [], "fullname": "app.Cust_Input.no_bud", "name": "no_bud", "type": {".class": "AnyType", "missing_import_name": null, "source_any": null, "type_of_any": 1}}}, "one_way": {".class": "SymbolTableNode", "implicit": true, "kind": "Mdef", "node": {".class": "Var", "flags": [], "fullname": "app.Cust_Input.one_way", "name": "one_way", "type": {".class": "AnyType", "missing_import_name": null, "source_any": null, "type_of_any": 1}}}, "response": {".class": "SymbolTableNode", "implicit": true, "kind": "Mdef", "node": {".class": "Var", "flags": [], "fullname": "app.Cust_Input.response", "name": "response", "type": {".class": "AnyType", "missing_import_name": null, "source_any": null, "type_of_any": 1}}}, "text": {".class": "SymbolTableNode", "implicit": true, "kind": "Mdef", "node": {".class": "Var", "flags": [], "fullname": "app.Cust_Input.text", "name": "text", "type": {".class": "AnyType", "missing_import_name": null, "source_any": null, "type_of_any": 1}}}}, "tuple_type": null, "type_vars": [], "typeddict_type": null}}, "Flask": {".class": "SymbolTableNode", "cross_ref": "flask.app.Flask", "kind": "Gdef"}, "SlackEventAdapter": {".class": "SymbolTableNode", "kind": "Gdef", "node": {".class": "Var", "flags": ["is_suppressed_import", "is_ready"], "fullname": "app.SlackEventAdapter", "name": "SlackEventAdapter", "type": {".class": "AnyType", "missing_import_name": "app.SlackEventAdapter", "source_any": null, "type_of_any": 3}}}, "WebClient": {".class": "SymbolTableNode", "kind": "Gdef", "node": {".class": "Var", "flags": ["is_suppressed_import", "is_ready"], "fullname": "app.WebClient", "name": "WebClient", "type": {".class": "AnyType", "missing_import_name": "app.WebClient", "source_any": null, "type_of_any": 3}}}, "__doc__": {".class": "SymbolTableNode", "kind": "Gdef", "node": {".class": "Var", "flags": ["is_ready"], "fullname": "app.__doc__", "name": "__doc__", "type": "builtins.str"}}, "__file__": {".class": "SymbolTableNode", "kind": "Gdef", "node": {".class": "Var", "flags": ["is_ready"], "fullname": "app.__file__", "name": "__file__", "type": "builtins.str"}}, "__name__": {".class": "SymbolTableNode", "kind": "Gdef", "node": {".class": "Var", "flags": ["is_ready"], "fullname": "app.__name__", "name": "__name__", "type": "builtins.str"}}, "__package__": {".class": "SymbolTableNode", "kind": "Gdef", "node": {".class": "Var", "flags": ["is_ready"], "fullname": "app.__package__", "name": "__package__", "type": "builtins.str"}}, "app": {".class": "SymbolTableNode", "kind": "Gdef", "node": {".class": "Var", "flags": [], "fullname": "app.app", "name": "app", "type": "flask.app.Flask"}}, "cbr": {".class": "SymbolTableNode", "cross_ref": "chat_bot_response", "kind": "Gdef"}, "certifi": {".class": "SymbolTableNode", "cross_ref": "certifi", "kind": "Gdef"}, "json": {".class": "SymbolTableNode", "cross_ref": "flask.json", "kind": "Gdef"}, "logging": {".class": "SymbolTableNode", "cross_ref": "logging", "kind": "Gdef"}, "message": {".class": "SymbolTableNode", "kind": "Gdef", "node": {".class": "Decorator", "func": {".class": "FuncDef", "arg_kinds": [0], "arg_names": ["payload"], "flags": ["is_decorated"], "fullname": "app.message", "name": "message", "type": null}, "is_overload": false, "var": {".class": "Var", "flags": ["is_ready"], "fullname": null, "name": "message", "type": {".class": "AnyType", "missing_import_name": "app.SlackEventAdapter", "source_any": {".class": "AnyType", "missing_import_name": "app.SlackEventAdapter", "source_any": null, "type_of_any": 3}, "type_of_any": 7}}}}, "os": {".class": "SymbolTableNode", "cross_ref": "os", "kind": "Gdef"}, "output": {".class": "SymbolTableNode", "kind": "Gdef", "node": {".class": "Var", "flags": [], "fullname": "app.output", "name": "output", "type": "typing.BinaryIO"}}, "p1": {".class": "SymbolTableNode", "kind": "Gdef", "node": {".class": "Var", "flags": [], "fullname": "app.p1", "name": "p1", "type": "app.Cust_Input"}}, "pickle": {".class": "SymbolTableNode", "cross_ref": "pickle", "kind": "Gdef"}, "request": {".class": "SymbolTableNode", "cross_ref": "flask.globals.request", "kind": "Gdef"}, "requests": {".class": "SymbolTableNode", "cross_ref": "requests", "kind": "Gdef"}, "slack_events_adapter": {".class": "SymbolTableNode", "kind": "Gdef", "node": {".class": "Var", "flags": [], "fullname": "app.slack_events_adapter", "name": "slack_events_adapter", "type": {".class": "AnyType", "missing_import_name": "app.SlackEventAdapter", "source_any": {".class": "AnyType", "missing_import_name": "app.SlackEventAdapter", "source_any": null, "type_of_any": 3}, "type_of_any": 7}}}, "slack_web_client": {".class": "SymbolTableNode", "kind": "Gdef", "node": {".class": "Var", "flags": [], "fullname": "app.slack_web_client", "name": "slack_web_client", "type": {".class": "AnyType", "missing_import_name": "app.WebClient", "source_any": {".class": "AnyType", "missing_import_name": "app.WebClient", "source_any": null, "type_of_any": 3}, "type_of_any": 7}}}, "sleep": {".class": "SymbolTableNode", "cross_ref": "time.sleep", "kind": "Gdef"}, "some_processing": {".class": "SymbolTableNode", "kind": "Gdef", "node": {".class": "FuncDef", "arg_kinds": [0], "arg_names": ["payload"], "flags": [], "fullname": "app.some_processing", "name": "some_processing", "type": null}}, "ssl_context": {".class": "SymbolTableNode", "kind": "Gdef", "node": {".class": "Var", "flags": [], "fullname": "app.ssl_context", "name": "ssl_context", "type": "ssl.SSLContext"}}, "ssl_lib": {".class": "SymbolTableNode", "cross_ref": "ssl", "kind": "Gdef"}, "threading": {".class": "SymbolTableNode", "cross_ref": "threading", "kind": "Gdef"}}, "path": "/home/dennis/Flight_Chatbot/app.py"}